vach/__init__.py
vach/cli.py
vach/defs.py
vach/excs.py
vach/optsargs.py
vach/utils.py
vach/vach.py
vach/yavault.py
vach-0.25.0.dist-info/licenses/LICENSE
vach-0.25.0.dist-info/METADATA
vach-0.25.0.dist-info/WHEEL
vach-0.25.0.dist-info/entry_points.txt
vach-0.25.0.dist-info/top_level.txt
vach-0.25.0.dist-info/RECORD
