Metadata-Version: 2.4
Name: vach
Version: 0.25.0
Summary: changing vault passwords
Author: terasik
Project-URL: Homepage, https://github.com/terasik/chvp
Classifier: Programming Language :: Python :: 3.9
Classifier: Programming Language :: Python :: 3.10
Classifier: Programming Language :: Python :: 3.11
Classifier: Programming Language :: Python :: 3.12
Classifier: License :: OSI Approved :: MIT License
Classifier: Operating System :: POSIX :: Linux
Requires-Python: >=3.9
License-File: LICENSE
Requires-Dist: argcomplete
Requires-Dist: ansible-vault
Requires-Dist: PyYAML
Dynamic: license-file
